tests/__init__.py
tests/models/__init__.py
tests/models/test_MB_PCA.py
tests/models/test_MB_PLS.py
tests/models/test_PCA.py
tests/models/test_PLS.py
tests/models/test_SMB_PLS.py
trendfitter/__init__.py
trendfitter/auxiliary/__init__.py
trendfitter/auxiliary/tf_aux.py
trendfitter/models/DiPLS.py
trendfitter/models/DyPCA.py
trendfitter/models/DyPLS.py
trendfitter/models/MB_PCA.py
trendfitter/models/MB_PLS.py
trendfitter/models/MLSMB_PLS.py
trendfitter/models/PCA.py
trendfitter/models/PLS.py
trendfitter/models/SMB_PLS.py
trendfitter/models/SO_PLS.py
trendfitter/models/__init__.py
trendfitter-0.0.6.dist-info/LICENSE
trendfitter-0.0.6.dist-info/METADATA
trendfitter-0.0.6.dist-info/WHEEL
trendfitter-0.0.6.dist-info/top_level.txt
trendfitter-0.0.6.dist-info/RECORD
