Metadata-Version: 2.1
Name: trendfitter
Version: 0.0.6
Summary: Latent Variable Modelling made easy
Home-page: https://github.com/danaraujocr/trendfitter
Author: Daniel Rodrigues
Author-email: dan.araujocr@gmail.com
License: UNKNOWN
Platform: UNKNOWN
Classifier: Programming Language :: Python :: 3
Classifier: License :: OSI Approved :: MIT License
Classifier: Operating System :: OS Independent
Requires-Python: >=3.7.4
Requires-Dist: numpy
Requires-Dist: pandas
Requires-Dist: scikit-learn
Requires-Dist: scipy
